README.md
setup.py
aws_resource_toggler.egg-info/PKG-INFO
aws_resource_toggler.egg-info/SOURCES.txt
aws_resource_toggler.egg-info/dependency_links.txt
aws_resource_toggler.egg-info/requires.txt
aws_resource_toggler.egg-info/top_level.txt
resource_toggler/__init__.py
resource_toggler/manager.py