Metadata-Version: 2.4
Name: aws-resource-toggler
Version: 0.1.0
Summary: A Python library to start and stop AWS resources (EC2, RDS, ECS) based on tags.
Home-page: https://github.com/yourusername/aws-resource-toggler
Author: Your Name or Company
License: MIT
Classifier: Programming Language :: Python :: 3
Classifier: License :: OSI Approved :: MIT License
Classifier: Operating System :: OS Independent
Classifier: Intended Audience :: Developers
Classifier: Topic :: System :: Systems Administration
Requires-Python: >=3.8
Requires-Dist: boto3>=1.34.0
Dynamic: author
Dynamic: classifier
Dynamic: description
Dynamic: description-content-type
Dynamic: home-page
Dynamic: license
Dynamic: requires-dist
Dynamic: requires-python
Dynamic: summary
